mock_the_python/mock_path.py
mock_the_python-0.1.1.dist-info/LICENSE
mock_the_python-0.1.1.dist-info/METADATA
mock_the_python-0.1.1.dist-info/WHEEL
mock_the_python-0.1.1.dist-info/RECORD
